trelawney/__init__.py
trelawney/base_explainer.py
trelawney/colors.py
trelawney/lime_explainer.py
trelawney/logreg_explainer.py
trelawney/shap_explainer.py
trelawney/surrogate_explainer.py
trelawney/tree_explainer.py
trelawney-0.3.1.dist-info/AUTHORS.rst
trelawney-0.3.1.dist-info/LICENSE
trelawney-0.3.1.dist-info/METADATA
trelawney-0.3.1.dist-info/WHEEL
trelawney-0.3.1.dist-info/top_level.txt
trelawney-0.3.1.dist-info/RECORD
