Metadata-Version: 2.1
Name: trelawney
Version: 0.3.1
Summary: Generic Interpretability package
Home-page: https://github.com/skanderkam/trelawney
Author: Skander Kamoun
Author-email: skander.kam2@gmail.com
License: MIT license
Keywords: trelawney
Platform: UNKNOWN
Classifier: Development Status :: 2 - Pre-Alpha
Classifier: Intended Audience :: Developers
Classifier: License :: OSI Approved :: MIT License
Classifier: Natural Language :: English
Classifier: Programming Language :: Python :: 3
Classifier: Programming Language :: Python :: 3.5
Classifier: Programming Language :: Python :: 3.6
Classifier: Programming Language :: Python :: 3.7
Requires-Python: >=3.5, !=3.0.*, !=3.1.*, !=3.2.*, !=3.3.*, !=3.4.*
Requires-Dist: numpy (==1.17.2)
Requires-Dist: pandas (==0.25.1)
Requires-Dist: tqdm (==4.36.1)
Requires-Dist: plotly (==4.1.1)
Requires-Dist: scikit-learn (==0.21.3)
Requires-Dist: xgboost (==0.90)
Requires-Dist: Keras (==2.3.0)
Requires-Dist: shap (==0.30.2)
Requires-Dist: lime (==0.1.1.36)
Requires-Dist: tensorflow (==1.15.2)
